odoo/addons/budget_control_advance_clearing/README.rst
odoo/addons/budget_control_advance_clearing/__init__.py
odoo/addons/budget_control_advance_clearing/__manifest__.py
odoo/addons/budget_control_advance_clearing/models/__init__.py
odoo/addons/budget_control_advance_clearing/models/account_move.py
odoo/addons/budget_control_advance_clearing/models/advance_budget_move.py
odoo/addons/budget_control_advance_clearing/models/base_budget_move.py
odoo/addons/budget_control_advance_clearing/models/budget_commit_forward.py
odoo/addons/budget_control_advance_clearing/models/budget_control.py
odoo/addons/budget_control_advance_clearing/models/budget_period.py
odoo/addons/budget_control_advance_clearing/models/expense_budget_move.py
odoo/addons/budget_control_advance_clearing/models/hr_expense.py
odoo/addons/budget_control_advance_clearing/readme/CONTRIBUTORS.md
odoo/addons/budget_control_advance_clearing/readme/DESCRIPTION.md
odoo/addons/budget_control_advance_clearing/report/__init__.py
odoo/addons/budget_control_advance_clearing/report/budget_common_monitoring.py
odoo/addons/budget_control_advance_clearing/report/budget_monitor_report.py
odoo/addons/budget_control_advance_clearing/security/ir.model.access.csv
odoo/addons/budget_control_advance_clearing/static/description/icon.png
odoo/addons/budget_control_advance_clearing/static/description/index.html
odoo/addons/budget_control_advance_clearing/tests/__init__.py
odoo/addons/budget_control_advance_clearing/tests/test_budget_advance.py
odoo/addons/budget_control_advance_clearing/views/advance_budget_move.xml
odoo/addons/budget_control_advance_clearing/views/budget_commit_forward_view.xml
odoo/addons/budget_control_advance_clearing/views/budget_control_view.xml
odoo/addons/budget_control_advance_clearing/views/budget_period_view.xml
odoo/addons/budget_control_advance_clearing/views/hr_expense_view.xml
odoo/addons/budget_control_advance_clearing/wizard/__init__.py
odoo_addon_budget_control_advance_clearing-18.0.1.2.0.dist-info/METADATA
odoo_addon_budget_control_advance_clearing-18.0.1.2.0.dist-info/WHEEL
odoo_addon_budget_control_advance_clearing-18.0.1.2.0.dist-info/top_level.txt
odoo_addon_budget_control_advance_clearing-18.0.1.2.0.dist-info/RECORD
